velosaurus_calc/__init__.py
velosaurus_calc/calculator.py
velosaurus_calc-1.0.11.dist-info/licenses/LICENSE
velosaurus_calc-1.0.11.dist-info/METADATA
velosaurus_calc-1.0.11.dist-info/WHEEL
velosaurus_calc-1.0.11.dist-info/top_level.txt
velosaurus_calc-1.0.11.dist-info/RECORD
