Metadata-Version: 2.4
Name: velosaurus_calc
Version: 1.0.11
Summary: Most awesome math package ever.
Home-page: https://github.com/OliverZott/python-devops-example
Author: Oliver Zott
Author-email: zott_oliver@web.de
Classifier: Development Status :: 4 - Beta
Classifier: Intended Audience :: Developers
Classifier: License :: OSI Approved :: MIT License
Classifier: Programming Language :: Python :: 3
Classifier: Programming Language :: Python :: 3.8
License-File: LICENSE
Dynamic: author
Dynamic: author-email
Dynamic: classifier
Dynamic: description
Dynamic: description-content-type
Dynamic: home-page
Dynamic: license-file
Dynamic: summary
